[{"id":702550,"name":"Lviv","lat":49.83826,"lng":24.02324,"elevation":0.0,"dstRules":""},{"id":700569,"name":"Mykolayiv","lat":46.97625,"lng":31.99296,"elevation":42.0,"dstRules":""},{"id":709717,"name":"Donetsk","lat":48.023,"lng":37.80224,"elevation":0.0,"dstRules":""},{"id":694423,"name":"Sevastopol","lat":44.60795,"lng":33.52134,"elevation":50.0,"dstRules":"MSK-3"},{"id":687700,"name":"Zaporizhzhya","lat":47.85167,"lng":35.11714,"elevation":105.0,"dstRules":""},{"id":701822,"name":"Mariupol","lat":47.09514,"lng":37.54131,"elevation":0.0,"dstRules":""},{"id":703448,"name":"Kyiv","lat":50.45466,"lng":30.5238,"elevation":0.0,"dstRules":""},{"id":703845,"name":"Kryvyy Rih","lat":47.90572,"lng":33.39404,"elevation":84.0,"dstRules":""},{"id":706483,"name":"Kharkiv","lat":49.98081,"lng":36.25272,"elevation":0.0,"dstRules":""},{"id":698740,"name":"Odesa","lat":46.48572,"lng":30.74383,"elevation":50.0,"dstRules":""},{"id":709930,"name":"Dnipro","lat":48.46664,"lng":35.04066,"elevation":120.0,"dstRules":""}]